web12982314/__init__.py
web12982314/web12982314.py
webcrawler_hgxd-0.1.dist-info/LICENSE.txt
webcrawler_hgxd-0.1.dist-info/METADATA
webcrawler_hgxd-0.1.dist-info/WHEEL
webcrawler_hgxd-0.1.dist-info/top_level.txt
webcrawler_hgxd-0.1.dist-info/RECORD
